ruopenrefs/__init__.py
ruopenrefs/exceptions.py
ruopenrefs/settings.py
ruopenrefs/providers/__init__.py
ruopenrefs/providers/_base.py
ruopenrefs/providers/_http.py
ruopenrefs/providers/mosru/__init__.py
ruopenrefs/providers/mosru/_base.py
ruopenrefs/providers/mosru/refs.py
tests/.env
tests/__init__.py
tests/test_mosru.py
ruopenrefs-0.2.0.dist-info/AUTHORS
ruopenrefs-0.2.0.dist-info/LICENSE
ruopenrefs-0.2.0.dist-info/METADATA
ruopenrefs-0.2.0.dist-info/WHEEL
ruopenrefs-0.2.0.dist-info/top_level.txt
ruopenrefs-0.2.0.dist-info/RECORD
