Metadata-Version: 2.1
Name: ruopenrefs
Version: 0.2.0
Summary: Общероссийские справочники из открытых источников
Home-page: https://github.com/idlesign/ruopenrefs
Author: Igor Starikov
Author-email: idlesign@yandex.ru
License: BSD 3-Clause License
Platform: UNKNOWN
Classifier: Development Status :: 4 - Beta
Classifier: Operating System :: OS Independent
Classifier: Programming Language :: Python
Classifier: Programming Language :: Python :: 3
Classifier: Programming Language :: Python :: 3.5
Classifier: Programming Language :: Python :: 3.6
Classifier: Programming Language :: Python :: 3.7
Classifier: License :: OSI Approved :: BSD License
Requires-Dist: envbox
Requires-Dist: requests
